hydra/__init__.py
hydra/base.py
hydra/challenge.py
hydra/clients.py
hydra/exceptions.py
hydra/hydra.py
hydra/jwk.py
hydra/oauth2.py
hydra_sdk-0.1.dev2.dist-info/DESCRIPTION.rst
hydra_sdk-0.1.dev2.dist-info/METADATA
hydra_sdk-0.1.dev2.dist-info/RECORD
hydra_sdk-0.1.dev2.dist-info/WHEEL
hydra_sdk-0.1.dev2.dist-info/metadata.json
hydra_sdk-0.1.dev2.dist-info/top_level.txt
hydra_sdk-0.1.dev2.dist-info/zip-safe
