Metadata-Version: 2.0
Name: hydra-sdk
Version: 0.1.dev2
Summary: Go Hydra SDK for Python
Home-page: http://www.ossystems.com.br
Author: O.S. Systems Software LTDA
Author-email: contato@ossystems.com.br
License: MIT
Keywords: hydra oauth2 openid go
Platform: UNKNOWN
Requires-Dist: pycrypto
Requires-Dist: python-jose
Requires-Dist: requests
